browser_use_sdk/__init__.py
browser_use_sdk/base_client.py
browser_use_sdk/billing/__init__.py
browser_use_sdk/billing/client.py
browser_use_sdk/billing/raw_client.py
browser_use_sdk/browsers/__init__.py
browser_use_sdk/browsers/client.py
browser_use_sdk/browsers/raw_client.py
browser_use_sdk/client.py
browser_use_sdk/core/__init__.py
browser_use_sdk/core/api_error.py
browser_use_sdk/core/client_wrapper.py
browser_use_sdk/core/datetime_utils.py
browser_use_sdk/core/file.py
browser_use_sdk/core/force_multipart.py
browser_use_sdk/core/http_client.py
browser_use_sdk/core/http_response.py
browser_use_sdk/core/jsonable_encoder.py
browser_use_sdk/core/pydantic_utilities.py
browser_use_sdk/core/query_encoder.py
browser_use_sdk/core/remove_none_from_dict.py
browser_use_sdk/core/request_options.py
browser_use_sdk/core/serialization.py
browser_use_sdk/core/unchecked_base_model.py
browser_use_sdk/environment.py
browser_use_sdk/errors/__init__.py
browser_use_sdk/errors/bad_request_error.py
browser_use_sdk/errors/forbidden_error.py
browser_use_sdk/errors/internal_server_error.py
browser_use_sdk/errors/not_found_error.py
browser_use_sdk/errors/payment_required_error.py
browser_use_sdk/errors/too_many_requests_error.py
browser_use_sdk/errors/unprocessable_entity_error.py
browser_use_sdk/files/__init__.py
browser_use_sdk/files/client.py
browser_use_sdk/files/raw_client.py
browser_use_sdk/lib/webhooks.py
browser_use_sdk/profiles/__init__.py
browser_use_sdk/profiles/client.py
browser_use_sdk/profiles/raw_client.py
browser_use_sdk/py.typed
browser_use_sdk/sessions/__init__.py
browser_use_sdk/sessions/client.py
browser_use_sdk/sessions/raw_client.py
browser_use_sdk/skills/__init__.py
browser_use_sdk/skills/client.py
browser_use_sdk/skills/raw_client.py
browser_use_sdk/skills_marketplace/__init__.py
browser_use_sdk/skills_marketplace/client.py
browser_use_sdk/skills_marketplace/raw_client.py
browser_use_sdk/tasks/__init__.py
browser_use_sdk/tasks/client.py
browser_use_sdk-2.0.14.dist-info/METADATA
browser_use_sdk-2.0.14.dist-info/WHEEL
browser_use_sdk-2.0.14.dist-info/RECORD
