Metadata-Version: 2.4
Name: browser-use-sdk
Version: 2.0.14
Summary: The official Python library for the Browser Use API
Requires-Python: >=3.8,<4.0
Classifier: Intended Audience :: Developers
Classifier: Operating System :: MacOS
Classifier: Operating System :: Microsoft :: Windows
Classifier: Operating System :: OS Independent
Classifier: Operating System :: POSIX
Classifier: Operating System :: POSIX :: Linux
Classifier: Programming Language :: Python
Classifier: Programming Language :: Python :: 3
Classifier: Programming Language :: Python :: 3.8
Classifier: Programming Language :: Python :: 3.9
Classifier: Programming Language :: Python :: 3.10
Classifier: Programming Language :: Python :: 3.11
Classifier: Programming Language :: Python :: 3.12
Classifier: Programming Language :: Python :: 3.13
Classifier: Programming Language :: Python :: 3.14
Classifier: Topic :: Software Development :: Libraries :: Python Modules
Classifier: Typing :: Typed
Requires-Dist: httpx (>=0.21.2)
Requires-Dist: pydantic (>=1.9.2)
Requires-Dist: pydantic-core (>=2.18.2)
Requires-Dist: typing_extensions (>=4.0.0)
Project-URL: Repository, https://github.com/browser-use/browser-use-python
